{
  "type": "forge:conditional",
  "recipes": [
    {
      "conditions": [
        {
          "type": "forge:mod_loaded",
          "modid": "wizards_reborn"
        }
      ],
      "recipe": {
         "type": "minecraft:crafting_shaped",
         "category": "building",
         "group": "cross_baulk",
         "pattern": [
           "#",
           "#",
           "#"
         ],
         "key": {
           "#": {
             "item": "minecraft:birch_log"
           }
         },
         "result": {
           "item": "silly_oddities:birch_baulk",
           "count": 6
         }
      }
    }
  ]
}
